gitsyncupstream/__init__.py
gitsyncupstream/__main__.py
gitsyncupstream/git.py
gitsyncupstream/py.typed
git_sync_upstream-1.0.5.dist-info/LICENSE
git_sync_upstream-1.0.5.dist-info/METADATA
git_sync_upstream-1.0.5.dist-info/WHEEL
git_sync_upstream-1.0.5.dist-info/entry_points.txt
git_sync_upstream-1.0.5.dist-info/top_level.txt
git_sync_upstream-1.0.5.dist-info/RECORD
